raypipe/__init__.py
raypipe/log.py
raypipe/UT/__init__.py
raypipe/UT/app/__init__.py
raypipe/UT/app/cnn_test.py
raypipe/applications/__init__.py
raypipe/applications/base.py
raypipe/applications/cnn.py
raypipe/cli/__init__.py
raypipe/core/__init__.py
raypipe/core/data_model.py
raypipe/core/model_proxy.py
raypipe/core/test_train.py
raypipe/core/distribution/__init__.py
raypipe/core/distribution/ps.py
raypipe/core/nn/__init__.py
raypipe/core/rpipe/__init__.py
raypipe/core/rpipe/decorator.py
raypipe/core/rpipe/utils.py
raypipe-1.0.0.dist-info/LICENSE
raypipe-1.0.0.dist-info/METADATA
raypipe-1.0.0.dist-info/WHEEL
raypipe-1.0.0.dist-info/entry_points.txt
raypipe-1.0.0.dist-info/top_level.txt
raypipe-1.0.0.dist-info/RECORD
