Metadata-Version: 2.1
Name: raypipe
Version: 1.0.0
Summary: Easy implementation and abstraction for train and deploy model on ray cluster
Home-page: https://github.com/billyyann/RayPipe
Author: Billy Yan
Author-email: 
License: UNKNOWN
Platform: UNKNOWN
Classifier: Programming Language :: Python :: 3
Classifier: License :: OSI Approved :: MIT License
Classifier: Operating System :: OS Independent
License-File: LICENSE
Requires-Dist: tensorflow-cpu (==2.3.0)
